<?xml version="1.0" encoding="UTF-8"?>
<Organisme id="tresorerie-84031-01" codeInsee="84031" dateMiseAJour="2015-09-09"
           pivotLocal="tresorerie">
   <Nom>Trésorerie de Carpentras</Nom>
   <EditeurSource>La Direction de l'information légale et administrative (Premier ministre)</EditeurSource>
   <Adresse type="géopostale">
      <Ligne>65 rue Sadolet</Ligne>
      <Ligne>CS 80029</Ligne>
      <CodePostal>84201</CodePostal>
      <NomCommune>Carpentras Cedex</NomCommune>
      <Localisation>
         <Latitude>44.051749</Latitude>
         <Longitude>5.0449636</Longitude>
         <Précision>8</Précision>
      </Localisation>
   </Adresse>
   <CoordonnéesNum>
      <Téléphone>+33 4 90 63 08 80</Téléphone>
      <Email>t084021@dgfip.finances.gouv.fr</Email>
      <Url>http://www.impots.gouv.fr</Url>
   </CoordonnéesNum>
</Organisme>