<?xml version="1.0" encoding="UTF-8"?>
<Organisme codeInsee="11266" dateMiseAJour="2015-11-03" id="permanence_juridique-11266-01" idPresta="52a71751b473e4724dea68a3" pivotLocal="permanence_juridique">
    <Nom>Point d&#39;accès au droit de Port-la-Nouvelle</Nom>
    <EditeurSource>Comarquage.fr</EditeurSource>
    <EditeurEMail>support-donnees@comarquage.fr</EditeurEMail>
    <Adresse type="géopostale">
        <Ligne>Lieu ressource insertion littoral</Ligne>
        <Ligne>222 rue de la Mairie</Ligne>
        <CodePostal>11210</CodePostal>
        <NomCommune>PORT LA NOUVELLE</NomCommune>
    </Adresse>
    <CoordonnéesNum>
        <Téléphone>+33 4 68 40 37 45</Téléphone>
        <Sve>http://www.justice.gouv.fr/sve</Sve>
    </CoordonnéesNum>
    <Ouverture>
        <PlageJ début="mercredi" fin="mercredi">
            <PlageH début="09:00:00" fin="12:00:00"/>
        </PlageJ>
    </Ouverture>
</Organisme>