<?xml version="1.0" encoding="UTF-8"?>
<Organisme id="sous_pref-02722-01" codeInsee="02722" dateMiseAJour="2013-11-13"
           pivotLocal="sous_pref">
   <Nom>Sous-préfecture - Soissons</Nom>
   <EditeurSource>La Direction de l'information légale et administrative (Premier ministre)</EditeurSource>
   <Adresse type="géopostale">
      <Ligne>2, rue Saint-Jean</Ligne>
      <CodePostal>02200</CodePostal>
      <NomCommune>Soissons</NomCommune>
      <Localisation>
         <Latitude>49.3775257</Latitude>
         <Longitude>3.3259264</Longitude>
         <Précision>6</Précision>
      </Localisation>
      <Accessibilité type="ACC"/>
   </Adresse>
   <CoordonnéesNum>
      <Téléphone>+33 3 23 59 88 00</Téléphone>
      <Télécopie>+33 3 23 74 56 51</Télécopie>
      <Email>sp-soissons@aisne.gouv.fr</Email>
      <Url>http://www.aisne.gouv.fr</Url>
   </CoordonnéesNum>
   <Ouverture>
      <PlageJ début="vendredi" fin="vendredi">
         <PlageH début="08:45:00" fin="12:00:00"/>
         <PlageH début="13:30:00" fin="16:15:00"/>
         <Note>Horaires de l'accueil téléphonique. Horaires des accueils sur place pour les guichets Cartes grises, permis de conduire, autres services : accueil lundi, mercredi, vendredi de 8h45 à 12h et de 13h30 à 16h15, mardi et jeudi de 8h45 à 12h et accueil sur rendez-vous les après-midi. Naturalisation / Étrangers : accueil du lundi matin au vendredi matin de 8h45 à 12h et accueil sur rendez-vous les après-midi. Permanence de la Banque de France : mardi et jeudi de 8h45 à 12h et de 13h30 à 16h15. Délégué du Défenseur des droits : sur rendez-vous au 03 23 59 88 04, audience : les lundis. Pour les autres services, la sous-préfecture est fermée mardi et jeudi après-midi sauf sur rendez-vous.</Note>
      </PlageJ>
      <PlageJ début="lundi" fin="lundi">
         <PlageH début="08:45:00" fin="12:00:00"/>
         <PlageH début="13:30:00" fin="16:15:00"/>
      </PlageJ>
      <PlageJ début="mardi" fin="mardi">
         <PlageH début="08:45:00" fin="12:00:00"/>
         <Note>(fermé l'après-midi, sauf sur rendez-vous)</Note>
      </PlageJ>
      <PlageJ début="mercredi" fin="mercredi">
         <PlageH début="08:45:00" fin="12:00:00"/>
         <PlageH début="13:30:00" fin="16:15:00"/>
      </PlageJ>
      <PlageJ début="jeudi" fin="jeudi">
         <PlageH début="08:45:00" fin="12:00:00"/>
         <Note>(fermé l'après-midi, sauf sur rendez-vous)</Note>
      </PlageJ>
   </Ouverture>
</Organisme>