<?xml version="1.0" encoding="UTF-8"?>
<Organisme id="commissariat_police-95018-01" codeInsee="95018" dateMiseAJour="2014-12-30"
           pivotLocal="commissariat_police">
   <Nom>Commissariat de police d'Argenteuil</Nom>
   <EditeurSource>Ministère de l'Intérieur</EditeurSource>
   <Adresse type="géopostale">
      <Ligne>21 avenue du Maréchal-Foch</Ligne>
      <CodePostal>95100</CodePostal>
      <NomCommune>Argenteuil</NomCommune>
      <Localisation>
         <Latitude>48.9451772</Latitude>
         <Longitude>2.2553826</Longitude>
         <Précision>8</Précision>
      </Localisation>
   </Adresse>
   <CoordonnéesNum>
      <Téléphone>+33 1 34 26 17 17</Téléphone>
      <Url>http://www.police-nationale.interieur.gouv.fr</Url>
      <Sve>http://www.interieur.gouv.fr/Contacter-une-brigade-de-gendarmerie-ou-un-commissariat-de-police</Sve>
   </CoordonnéesNum>
</Organisme>