<?xml version="1.0" encoding="UTF-8"?>
<Organisme id="gendarmerie-43033-01" codeInsee="43033" dateMiseAJour="2015-05-05"
           pivotLocal="gendarmerie">
   <Nom>Brigade de proximité de gendarmerie de Blesle</Nom>
   <EditeurSource>Ministère de l'Intérieur</EditeurSource>
   <Adresse type="géopostale">
      <Ligne>La Bessière</Ligne>
      <CodePostal>43450</CodePostal>
      <NomCommune>Blesle</NomCommune>
      <Localisation>
         <Latitude>45.312829</Latitude>
         <Longitude>3.1753</Longitude>
         <Précision>6</Précision>
      </Localisation>
   </Adresse>
   <CoordonnéesNum>
      <Téléphone>+33 4 71 76 21 19</Téléphone>
      <Télécopie>+33 4 71 76 28 83</Télécopie>
      <Url>http://www.gendarmerie.interieur.gouv.fr</Url>
      <Sve>http://www.interieur.gouv.fr/Contacter-une-brigade-de-gendarmerie-ou-un-commissariat-de-police</Sve>
   </CoordonnéesNum>
</Organisme>