<?xml version="1.0" encoding="UTF-8"?>
<Organisme id="gendarmerie-66082-01" codeInsee="66082" dateMiseAJour="2013-07-10"
           pivotLocal="gendarmerie">
   <Nom>Brigade de proximité de gendarmerie de Formiguères</Nom>
   <EditeurSource>Ministère de l'Intérieur</EditeurSource>
   <Adresse type="géopostale">
      <Ligne>4 Carrere de la Montagnette</Ligne>
      <CodePostal>66210</CodePostal>
      <NomCommune>Formiguères</NomCommune>
      <Localisation>
         <Latitude>42.61396</Latitude>
         <Longitude>2.102634</Longitude>
         <Précision>4</Précision>
      </Localisation>
   </Adresse>
   <CoordonnéesNum>
      <Téléphone>+33 4 68 04 40 01</Téléphone>
      <Email>cob.font-romeu-odeillo-via@gendarmerie.interieur.gouv.fr</Email>
      <Url>http://www.gendarmerie.interieur.gouv.fr</Url>
      <Sve>http://www.interieur.gouv.fr/Contacter-une-brigade-de-gendarmerie-ou-un-commissariat-de-police</Sve>
   </CoordonnéesNum>
</Organisme>