<?xml version="1.0" encoding="UTF-8"?>
<Organisme id="epci-34178-01" codeInsee="34178" dateMiseAJour="2015-05-12"
           pivotLocal="epci">
   <Nom>Communauté de communes Orb et Taurou</Nom>
   <EditeurSource>La Direction de l'information légale et administrative (Premier ministre)</EditeurSource>
   <Adresse type="géopostale">
      <Ligne>27 bis avenue de la République</Ligne>
      <CodePostal>34490</CodePostal>
      <NomCommune>Murviel-lès-Béziers</NomCommune>
      <Localisation>
         <Latitude>43.4747814</Latitude>
         <Longitude>3.08567990000006</Longitude>
         <Précision>6</Précision>
      </Localisation>
      <Accessibilité type="ACC"/>
   </Adresse>
   <CoordonnéesNum>
      <Téléphone>+33 4 67 32 44 68</Téléphone>
      <Télécopie>+33 4 67 39 46 35</Télécopie>
      <Email>communaute-orb-et-taurou@wanadoo.fr</Email>
   </CoordonnéesNum>
   <Ouverture>
      <PlageJ début="lundi" fin="jeudi">
         <PlageH début="09:00:00" fin="12:00:00"/>
         <PlageH début="13:30:00" fin="17:30:00"/>
      </PlageJ>
      <PlageJ début="vendredi" fin="vendredi">
         <PlageH début="09:00:00" fin="12:00:00"/>
      </PlageJ>
   </Ouverture>
</Organisme>