<?xml version="1.0" encoding="UTF-8"?>
<Organisme id="gendarmerie-34194-01" codeInsee="34194" dateMiseAJour="2015-05-05"
           pivotLocal="gendarmerie">
   <Nom>Brigade de proximité de gendarmerie de Paulhan</Nom>
   <EditeurSource>Ministère de l'Intérieur</EditeurSource>
   <Adresse type="géopostale">
      <Ligne>78 cours National</Ligne>
      <CodePostal>34230</CodePostal>
      <NomCommune>Paulhan</NomCommune>
      <Localisation>
         <Latitude>43.5391397</Latitude>
         <Longitude>3.4571945</Longitude>
         <Précision>8</Précision>
      </Localisation>
   </Adresse>
   <CoordonnéesNum>
      <Téléphone>+33 4 67 25 21 27</Téléphone>
      <Télécopie>+33 4 67 25 21 77</Télécopie>
      <Url>http://www.gendarmerie.interieur.gouv.fr</Url>
      <Sve>http://www.interieur.gouv.fr/Contacter-une-brigade-de-gendarmerie-ou-un-commissariat-de-police</Sve>
   </CoordonnéesNum>
</Organisme>