<?xml version="1.0" encoding="UTF-8"?>
<Organisme id="clic-13208-01" codeInsee="13208" dateMiseAJour="2015-04-29"
           pivotLocal="clic"
           idPresta="clic-89">
   <Nom>Point d'information local dédié aux personnes âgées - Marseille</Nom>
   <EditeurSource>Caisse nationale de solidarité pour l'autonomie</EditeurSource>
   <Adresse type="géopostale">
      <Ligne>Centre local d'information et de coordination Sud harmonie</Ligne>
      <Ligne>5 rue de Cassis</Ligne>
      <CodePostal>13008</CodePostal>
      <NomCommune>Marseille</NomCommune>
      <Localisation>
         <Latitude>43.279407</Latitude>
         <Longitude>5.388105</Longitude>
         <Précision>8</Précision>
      </Localisation>
   </Adresse>
   <CoordonnéesNum>
      <Téléphone>+33 4 91 91 27 27</Téléphone>
      <Email>clic@assistancefamiliale.com</Email>
   </CoordonnéesNum>
   <Ouverture>
      <PlageJ début="lundi" fin="vendredi">
         <PlageH début="09:00:00" fin="13:00:00"/>
         <PlageH début="14:00:00" fin="17:00:00"/>
      </PlageJ>
   </Ouverture>
   <Commentaire>Téléphoner pour convenir d'un rendez-vous avant de se rendre sur place.</Commentaire>
</Organisme>