<?xml version="1.0" encoding="UTF-8"?>
<Organisme id="rectorat-51454-01" codeInsee="51454" dateMiseAJour="2015-12-15"
           pivotLocal="rectorat">
   <Nom>Rectorat - Académie de Reims</Nom>
   <EditeurSource>La Direction de l'information légale et administrative (Premier ministre)</EditeurSource>
   <Adresse type="géopostale">
      <Ligne>1, rue Navier</Ligne>
      <CodePostal>51082</CodePostal>
      <NomCommune>Reims Cedex</NomCommune>
      <Localisation>
         <Latitude>49.2445865</Latitude>
         <Longitude>4.04</Longitude>
         <Précision>8</Précision>
      </Localisation>
      <Accessibilité type="ACC"/>
   </Adresse>
   <CoordonnéesNum>
      <Téléphone>+33 3 26 05 69 69</Téléphone>
      <Télécopie>+33 3 26 05 69 42</Télécopie>
      <Url>http://www.ac-reims.fr</Url>
   </CoordonnéesNum>
   <Ouverture>
      <PlageJ début="lundi" fin="vendredi">
         <PlageH début="08:30:00" fin="12:30:00"/>
         <PlageH début="13:30:00" fin="17:00:00"/>
      </PlageJ>
   </Ouverture>
</Organisme>