<?xml version="1.0" encoding="UTF-8"?>
<Organisme id="gendarmerie-16167-01" codeInsee="16167" dateMiseAJour="2015-03-17"
           pivotLocal="gendarmerie">
   <Nom>Brigade de proximité de gendarmerie de Jarnac</Nom>
   <EditeurSource>Ministère de l'Intérieur</EditeurSource>
   <Adresse type="géopostale">
      <Ligne>24 rue de Dogliani</Ligne>
      <CodePostal>16200</CodePostal>
      <NomCommune>Jarnac</NomCommune>
      <Localisation>
         <Latitude>45.6826072</Latitude>
         <Longitude>-0.1698868</Longitude>
         <Précision>8</Précision>
      </Localisation>
   </Adresse>
   <CoordonnéesNum>
      <Téléphone>+33 5 45 81 45 73</Téléphone>
      <Télécopie>+33 5 45 81 45 76</Télécopie>
      <Url>http://www.gendarmerie.interieur.gouv.fr</Url>
      <Sve>http://www.interieur.gouv.fr/Contacter-une-brigade-de-gendarmerie-ou-un-commissariat-de-police</Sve>
   </CoordonnéesNum>
</Organisme>