<?xml version="1.0" encoding="UTF-8"?>
<Organisme codeInsee="16102" dateMiseAJour="2014-01-28" id="ti-16102-01" idPresta="4cac9ed7293594648a00ee2e" pivotLocal="ti">
    <Nom>Tribunal d&#39;instance de Cognac</Nom>
    <EditeurSource>Ministère de la justice</EditeurSource>
    <EditeurEMail>support-donnees@comarquage.fr</EditeurEMail>
    <Adresse type="géopostale">
        <Ligne>3 rue Pierre Martin Civat</Ligne>
        <CodePostal>16100</CodePostal>
        <NomCommune>COGNAC</NomCommune>
        <Localisation>
            <Latitude>45.6915945</Latitude>
            <Longitude>-0.3280112</Longitude>
            <Précision>8</Précision>
        </Localisation>
    </Adresse>
    <CoordonnéesNum>
        <Téléphone>+33 5 45 82 06 75</Téléphone>
        <Télécopie>+33 5 45 82 88 15</Télécopie>
        <Url>http://www.justice.gouv.fr/</Url>
        <Sve>http://www.justice.gouv.fr/sve</Sve>
    </CoordonnéesNum>
    <Ouverture>
        <PlageJ début="lundi" fin="lundi">
            <PlageH début="09:00:00" fin="17:00:00"/>
        </PlageJ>
        <PlageJ début="mardi" fin="mardi">
            <PlageH début="08:30:00" fin="17:00:00"/>
        </PlageJ>
        <PlageJ début="mercredi" fin="mercredi">
            <PlageH début="09:00:00" fin="17:00:00"/>
        </PlageJ>
        <PlageJ début="jeudi" fin="jeudi">
            <PlageH début="08:30:00" fin="17:00:00"/>
        </PlageJ>
        <PlageJ début="vendredi" fin="vendredi">
            <PlageH début="09:00:00" fin="17:00:00"/>
        </PlageJ>
    </Ouverture>
</Organisme>