<?xml version="1.0" encoding="UTF-8"?>
<Organisme id="crib-42218-01" codeInsee="42218" dateMiseAJour="2016-03-10"
           pivotLocal="crib">
   <Nom>Centre de ressources et d'information des bénévoles (Crib) - Comité départemental olympique et sportif de la Loire</Nom>
   <EditeurSource>La Direction de l'information légale et administrative (Premier ministre)</EditeurSource>
   <Adresse type="géopostale">
      <Ligne>4 rue des Trois-Meules</Ligne>
      <Ligne>Maison départementale des sports</Ligne>
      <Ligne>BP 90144</Ligne>
      <CodePostal>42012</CodePostal>
      <NomCommune>Saint-Étienne Cedex 2</NomCommune>
      <Localisation>
         <Latitude>45.4222365</Latitude>
         <Longitude>4.3937267</Longitude>
         <Précision>8</Précision>
      </Localisation>
      <Accessibilité type="ACC"/>
   </Adresse>
   <CoordonnéesNum>
      <Téléphone>+33 4 77 59 56 02</Téléphone>
      <Télécopie>+33 4 77 59 56 06</Télécopie>
      <Email>crib@maisondessportsloire.com</Email>
      <Url>http://loire.franceolympique.com</Url>
   </CoordonnéesNum>
   <Ouverture>
      <PlageJ début="lundi" fin="jeudi">
         <PlageH début="08:00:00" fin="17:00:00"/>
      </PlageJ>
      <PlageJ début="vendredi" fin="vendredi">
         <PlageH début="09:00:00" fin="16:00:00"/>
      </PlageJ>
   </Ouverture>
</Organisme>