<?xml version="1.0" encoding="UTF-8"?>
<Organisme id="gendarmerie-42204-01" codeInsee="42204" dateMiseAJour="2015-05-05"
           pivotLocal="gendarmerie">
   <Nom>Brigade de proximité de gendarmerie de Saint-Bonnet-le-Château</Nom>
   <EditeurSource>Ministère de l'Intérieur</EditeurSource>
   <Adresse type="géopostale">
      <Ligne>1 boulevard du Haut-Forez</Ligne>
      <CodePostal>42380</CodePostal>
      <NomCommune>Saint-Bonnet-le-Château</NomCommune>
      <Localisation>
         <Latitude>45.4243145</Latitude>
         <Longitude>4.0632029</Longitude>
         <Précision>6</Précision>
      </Localisation>
   </Adresse>
   <CoordonnéesNum>
      <Téléphone>+33 4 77 50 09 58</Téléphone>
      <Télécopie>+33 4 77 50 54 97</Télécopie>
      <Url>http://www.gendarmerie.interieur.gouv.fr</Url>
      <Sve>http://www.interieur.gouv.fr/Contacter-une-brigade-de-gendarmerie-ou-un-commissariat-de-police</Sve>
   </CoordonnéesNum>
</Organisme>