<?xml version="1.0" encoding="UTF-8"?>
<Organisme id="pole_emploi-73011-01" codeInsee="73011" dateMiseAJour="2015-09-09"
           pivotLocal="pole_emploi">
   <Nom>Pôle emploi d'Albertville</Nom>
   <EditeurSource>La Direction de l'information légale et administrative (Premier ministre)</EditeurSource>
   <Adresse type="géopostale">
      <Ligne>45 avenue Jean-Jaurès</Ligne>
      <Ligne>BP 96</Ligne>
      <CodePostal>73203</CodePostal>
      <NomCommune>Albertville Cedex</NomCommune>
      <Localisation>
         <Latitude>45.6709192</Latitude>
         <Longitude>6.3875097</Longitude>
         <Précision>8</Précision>
      </Localisation>
   </Adresse>
   <CoordonnéesNum>
      <Téléphone coût="Numéro violet ou majoré : prix d'un appel + service gratuit. Depuis l’étranger, vous pouvez composer le +33 1 77 86 39 49. Employeur : 3995. Depuis l'étranger, composez le +33 1 77 86 39 95.">3949</Téléphone>
      <Url>http://www.pole-emploi.fr</Url>
   </CoordonnéesNum>
   <Ouverture>
      <PlageJ début="mercredi" fin="mercredi">
         <PlageH début="13:30:00" fin="16:15:00"/>
      </PlageJ>
      <PlageJ début="lundi" fin="mardi">
         <PlageH début="08:30:00" fin="12:30:00"/>
         <PlageH début="13:30:00" fin="16:15:00"/>
      </PlageJ>
      <PlageJ début="jeudi" fin="jeudi">
         <PlageH début="08:30:00" fin="12:30:00"/>
         <PlageH début="13:30:00" fin="16:15:00"/>
      </PlageJ>
      <PlageJ début="vendredi" fin="vendredi">
         <PlageH début="08:30:00" fin="12:30:00"/>
      </PlageJ>
   </Ouverture>
</Organisme>