<?xml version="1.0" encoding="UTF-8"?>
<Organisme id="clic-44036-01" codeInsee="44036" dateMiseAJour="2015-04-29"
           pivotLocal="clic"
           idPresta="clic-331">
   <Nom>Point d'information local dédié aux personnes âgées - Chateaubriant</Nom>
   <EditeurSource>Caisse nationale de solidarité pour l'autonomie</EditeurSource>
   <Adresse type="géopostale">
      <Ligne>13 rue d'Angers</Ligne>
      <Ligne>Centre local d'information et de coordination du Pays de Chateaubriant</Ligne>
      <CodePostal>44110</CodePostal>
      <NomCommune>Châteaubriant</NomCommune>
      <Localisation>
         <Latitude>48.856614</Latitude>
         <Longitude>2.352222</Longitude>
         <Précision>8</Précision>
      </Localisation>
   </Adresse>
   <CoordonnéesNum>
      <Téléphone>+33 2 28 04 05 85</Téléphone>
      <Email>clicdupaysdechateaubriant@wanadoo.fr</Email>
   </CoordonnéesNum>
   <Ouverture>
      <PlageJ début="lundi" fin="vendredi">
         <PlageH début="09:00:00" fin="12:00:00"/>
      </PlageJ>
   </Ouverture>
   <Commentaire>Téléphoner pour convenir d'un rendez-vous avant de se rendre sur place.</Commentaire>
</Organisme>