<?xml version="1.0" encoding="UTF-8"?>
<Organisme id="gendarmerie-35068-01" codeInsee="35068" dateMiseAJour="2015-05-05"
           pivotLocal="gendarmerie">
   <Nom>Brigade de proximité de gendarmerie de Châteaubourg</Nom>
   <EditeurSource>Ministère de l'Intérieur</EditeurSource>
   <Adresse type="géopostale">
      <Ligne>67 rue de Paris</Ligne>
      <CodePostal>35220</CodePostal>
      <NomCommune>Châteaubourg</NomCommune>
      <Localisation>
         <Latitude>48.1100198</Latitude>
         <Longitude>-1.3977205</Longitude>
         <Précision>8</Précision>
      </Localisation>
   </Adresse>
   <CoordonnéesNum>
      <Téléphone>+33 2 99 00 31 04</Téléphone>
      <Url>http://www.gendarmerie.interieur.gouv.fr</Url>
      <Sve>http://www.interieur.gouv.fr/Contacter-une-brigade-de-gendarmerie-ou-un-commissariat-de-police</Sve>
   </CoordonnéesNum>
</Organisme>