<?xml version="1.0" encoding="UTF-8"?>
<Organisme id="gendarmerie-97214-01" codeInsee="97214" dateMiseAJour="2013-07-10"
           pivotLocal="gendarmerie">
   <Nom>Brigade de proximité de gendarmerie du Lorrain</Nom>
   <EditeurSource>Ministère de l'Intérieur</EditeurSource>
   <Adresse type="géopostale">
      <Ligne>Avenue du Général-de-Gaulle</Ligne>
      <CodePostal>97214</CodePostal>
      <NomCommune>Lorrain</NomCommune>
   </Adresse>
   <CoordonnéesNum>
      <Téléphone>+596 5 96 53 26 19</Téléphone>
      <Télécopie>+596 5 96 53 26 21</Télécopie>
      <Email>cob.le-lorrain@gendarmerie.interieur.gouv.fr</Email>
      <Url>http://www.gendarmerie.interieur.gouv.fr</Url>
      <Sve>http://www.interieur.gouv.fr/Contacter-une-brigade-de-gendarmerie-ou-un-commissariat-de-police</Sve>
   </CoordonnéesNum>
</Organisme>