<?xml version="1.0" encoding="UTF-8"?>
<Organisme id="mairie-05091-01" codeInsee="05091" dateMiseAJour="2014-12-29"
           pivotLocal="mairie">
   <Nom>Mairie de Moydans</Nom>
   <EditeurSource>La Direction de l'information légale et administrative (Premier ministre)</EditeurSource>
   <Adresse type="géopostale">
      <Ligne>Route de Nyons</Ligne>
      <CodePostal>05150</CodePostal>
      <NomCommune>Moydans</NomCommune>
      <Localisation>
         <Latitude>44.399702</Latitude>
         <Longitude>5.503793</Longitude>
         <Précision>8</Précision>
      </Localisation>
      <Accessibilité type="NAC"/>
   </Adresse>
   <CoordonnéesNum>
      <Téléphone>+33 4 92 66 62 51</Téléphone>
      <Télécopie>+33 4 92 66 62 51</Télécopie>
      <Email>mairie.moydans@wanadoo.fr</Email>
   </CoordonnéesNum>
   <Ouverture>
      <PlageJ début="mardi" fin="mardi">
         <PlageH début="14:00:00" fin="18:00:00"/>
      </PlageJ>
   </Ouverture>
</Organisme>