<?xml version="1.0" encoding="UTF-8"?>
<Organisme id="mairie-24475-01" codeInsee="24475" dateMiseAJour="2016-02-08"
           pivotLocal="mairie">
   <Nom>Mairie de Saint-Pantaly-d'Ans</Nom>
   <EditeurSource>La Direction de l'information légale et administrative (Premier ministre)</EditeurSource>
   <Adresse type="géopostale">
      <Ligne>Le Bourg</Ligne>
      <CodePostal>24640</CodePostal>
      <NomCommune>Saint-Pantaly-d'Ans</NomCommune>
      <Localisation>
         <Latitude>45.2705612183</Latitude>
         <Longitude>1.05976605415</Longitude>
         <Précision>6</Précision>
      </Localisation>
      <Accessibilité type="ACC"/>
   </Adresse>
   <CoordonnéesNum>
      <Téléphone>+33 5 53 05 31 37</Téléphone>
      <Email>mairiesaintpantalydans@orange.fr</Email>
   </CoordonnéesNum>
   <Ouverture>
      <PlageJ début="mardi" fin="vendredi">
         <PlageH début="09:00:00" fin="13:00:00"/>
      </PlageJ>
   </Ouverture>
</Organisme>