<?xml version="1.0" encoding="UTF-8"?>
<Organisme id="mairie-26327-01" codeInsee="26327" dateMiseAJour="2015-07-08"
           pivotLocal="mairie">
   <Nom>Mairie de Saint-Roman</Nom>
   <EditeurSource>La Direction de l'information légale et administrative (Premier ministre)</EditeurSource>
   <Adresse type="géopostale">
      <Ligne>Le Village</Ligne>
      <CodePostal>26410</CodePostal>
      <NomCommune>Saint-Roman</NomCommune>
      <Localisation>
         <Latitude>44.690773</Latitude>
         <Longitude>5.4326745</Longitude>
         <Précision>8</Précision>
      </Localisation>
      <Accessibilité type="ACC"/>
   </Adresse>
   <CoordonnéesNum>
      <Téléphone>+33 4 75 21 81 40</Téléphone>
      <Télécopie>+33 4 75 21 81 40</Télécopie>
      <Email>mairie.saintroman@orange.fr</Email>
      <Url>http://www.saint-roman.fr</Url>
   </CoordonnéesNum>
   <Ouverture>
      <PlageJ début="mardi" fin="mardi">
         <PlageH début="13:00:00" fin="17:00:00"/>
      </PlageJ>
      <PlageJ début="vendredi" fin="vendredi">
         <PlageH début="09:00:00" fin="12:00:00"/>
      </PlageJ>
   </Ouverture>
</Organisme>