<?xml version="1.0" encoding="UTF-8"?>
<Organisme id="mairie-59254-01" codeInsee="59254" dateMiseAJour="2015-08-12"
           pivotLocal="mairie">
   <Nom>Mairie de Fressain</Nom>
   <EditeurSource>La Direction de l'information légale et administrative (Premier ministre)</EditeurSource>
   <Adresse type="géopostale">
      <Ligne>2 place du Général-de-Gaulle</Ligne>
      <CodePostal>59234</CodePostal>
      <NomCommune>Fressain</NomCommune>
      <Localisation>
         <Latitude>50.2874468</Latitude>
         <Longitude>3.1933339</Longitude>
         <Précision>9</Précision>
      </Localisation>
      <Accessibilité type="ACC"/>
   </Adresse>
   <CoordonnéesNum>
      <Téléphone>+33 3 27 80 90 42</Téléphone>
      <Télécopie>+33 3 27 80 85 23</Télécopie>
      <Email>fressain@wanadoo.fr</Email>
   </CoordonnéesNum>
   <Ouverture>
      <PlageJ début="jeudi" fin="samedi">
         <PlageH début="08:30:00" fin="12:00:00"/>
         <Note>Accueil fermé le samedi pendant juillet-août.</Note>
      </PlageJ>
      <PlageJ début="lundi" fin="lundi">
         <PlageH début="08:30:00" fin="12:00:00"/>
      </PlageJ>
      <PlageJ début="mardi" fin="mardi">
         <PlageH début="08:30:00" fin="12:00:00"/>
         <PlageH début="14:00:00" fin="16:00:00"/>
         <Note>Accueil fermé l'après-midi pendant juillet-août.</Note>
      </PlageJ>
   </Ouverture>
</Organisme>