<?xml version="1.0" encoding="UTF-8"?>
<Organisme id="gendarmerie-40312-01" codeInsee="40312" dateMiseAJour="2015-05-05"
           pivotLocal="gendarmerie">
   <Nom>Brigade de proximité de gendarmerie de Tarnos</Nom>
   <EditeurSource>Ministère de l'Intérieur</EditeurSource>
   <Adresse type="géopostale">
      <Ligne>17 route Nationale 10</Ligne>
      <CodePostal>40220</CodePostal>
      <NomCommune>Tarnos</NomCommune>
      <Localisation>
         <Latitude>43.5501933</Latitude>
         <Longitude>-1.4603856</Longitude>
         <Précision>8</Précision>
      </Localisation>
   </Adresse>
   <CoordonnéesNum>
      <Téléphone>+33 5 59 64 36 49</Téléphone>
      <Télécopie>+33 5 59 64 36 56</Télécopie>
      <Url>http://www.gendarmerie.interieur.gouv.fr</Url>
      <Sve>http://www.interieur.gouv.fr/Contacter-une-brigade-de-gendarmerie-ou-un-commissariat-de-police</Sve>
   </CoordonnéesNum>
</Organisme>