<?xml version="1.0" encoding="UTF-8"?>
<Organisme id="mairie-48103-01" codeInsee="48103" dateMiseAJour="2015-07-06"
           pivotLocal="mairie">
   <Nom>Mairie de Montrodat</Nom>
   <EditeurSource>La Direction de l'information légale et administrative (Premier ministre)</EditeurSource>
   <Adresse type="géopostale">
      <Ligne>Le Village</Ligne>
      <CodePostal>48100</CodePostal>
      <NomCommune>Montrodat</NomCommune>
      <Localisation>
         <Latitude>44.5519</Latitude>
         <Longitude>3.329055</Longitude>
         <Précision>6</Précision>
      </Localisation>
      <Accessibilité type="ACC"/>
   </Adresse>
   <CoordonnéesNum>
      <Téléphone>+33 4 66 32 10 68</Téléphone>
      <Télécopie>+33 4 66 32 45 36</Télécopie>
      <Email>mairie.montrodat@wanadoo.fr</Email>
      <Url>http://www.montrodat.fr</Url>
   </CoordonnéesNum>
   <Ouverture>
      <PlageJ début="lundi" fin="vendredi">
         <PlageH début="08:30:00" fin="12:00:00"/>
         <PlageH début="13:30:00" fin="17:00:00"/>
      </PlageJ>
   </Ouverture>
</Organisme>