<?xml version="1.0" encoding="UTF-8"?>
<Organisme id="gendarmerie-55498-01" codeInsee="55498" dateMiseAJour="2015-05-19"
           pivotLocal="gendarmerie">
   <Nom>Brigade de proximité de gendarmerie de Souilly</Nom>
   <EditeurSource>Ministère de l'Intérieur</EditeurSource>
   <Adresse type="géopostale">
      <Ligne>54 Voie Sacrée</Ligne>
      <CodePostal>55220</CodePostal>
      <NomCommune>Souilly</NomCommune>
      <Localisation>
         <Latitude>49.030599</Latitude>
         <Longitude>5.287961</Longitude>
         <Précision>8</Précision>
      </Localisation>
   </Adresse>
   <CoordonnéesNum>
      <Téléphone>+33 3 29 80 50 02</Téléphone>
      <Télécopie>+33 3 29 80 58 59</Télécopie>
      <Url>http://www.gendarmerie.interieur.gouv.fr</Url>
      <Sve>http://www.interieur.gouv.fr/Contacter-une-brigade-de-gendarmerie-ou-un-commissariat-de-police</Sve>
   </CoordonnéesNum>
</Organisme>