<?xml version="1.0" encoding="UTF-8"?>
<Organisme codeInsee="55545" dateMiseAJour="2014-01-28" id="ti-55545-01" idPresta="4cac9e62293594648a000653" pivotLocal="ti">
    <Nom>Tribunal d&#39;instance de Verdun</Nom>
    <EditeurSource>Ministère de la justice</EditeurSource>
    <EditeurEMail>support-donnees@comarquage.fr</EditeurEMail>
    <Adresse type="géopostale">
        <Ligne>place Saint-Paul</Ligne>
        <CodePostal>55107</CodePostal>
        <NomCommune>VERDUN CEDEX</NomCommune>
        <Localisation>
            <Latitude>49.163768</Latitude>
            <Longitude>5.3844849</Longitude>
            <Précision>6</Précision>
        </Localisation>
    </Adresse>
    <CoordonnéesNum>
        <Téléphone>+33 3 29 86 88 00</Téléphone>
        <Télécopie>+33 3 29 86 77 18</Télécopie>
        <Url>http://www.justice.gouv.fr/</Url>
        <Sve>http://www.justice.gouv.fr/sve</Sve>
    </CoordonnéesNum>
    <Ouverture>
        <PlageJ début="lundi" fin="vendredi">
            <PlageH début="08:30:00" fin="12:00:00"/>
            <PlageH début="14:00:00" fin="16:00:00"/>
        </PlageJ>
    </Ouverture>
</Organisme>