<?xml version="1.0" encoding="UTF-8"?>
<Organisme id="mairie-01398-01" codeInsee="01398" dateMiseAJour="2015-07-08"
           pivotLocal="mairie">
   <Nom>Mairie de Savigneux</Nom>
   <EditeurSource>La Direction de l'information légale et administrative (Premier ministre)</EditeurSource>
   <Adresse type="géopostale">
      <Ligne>Rue de l'Église</Ligne>
      <CodePostal>01480</CodePostal>
      <NomCommune>Savigneux</NomCommune>
      <Localisation>
         <Latitude>46.0032997131</Latitude>
         <Longitude>4.85249996185</Longitude>
         <Précision>8</Précision>
      </Localisation>
      <Accessibilité type="ACC"/>
   </Adresse>
   <CoordonnéesNum>
      <Téléphone>+33 4 74 00 70 84</Téléphone>
      <Télécopie>+33 4 74 00 76 58</Télécopie>
      <Email>accueil@mairiesavigneux.fr</Email>
   </CoordonnéesNum>
   <Ouverture>
      <PlageJ début="vendredi" fin="vendredi">
         <PlageH début="09:00:00" fin="11:30:00"/>
      </PlageJ>
      <PlageJ début="jeudi" fin="mercredi">
         <PlageH début="13:30:00" fin="16:00:00"/>
      </PlageJ>
      <PlageJ début="lundi" fin="mardi">
         <PlageH début="13:30:00" fin="16:00:00"/>
      </PlageJ>
      <PlageJ début="samedi" fin="samedi">
         <PlageH début="09:00:00" fin="11:00:00"/>
      </PlageJ>
   </Ouverture>
</Organisme>