<?xml version="1.0" encoding="UTF-8"?>
<Organisme id="mairie-02303-01" codeInsee="02303" dateMiseAJour="2015-07-08"
           pivotLocal="mairie">
   <Nom>Mairie de Fayet</Nom>
   <EditeurSource>La Direction de l'information légale et administrative (Premier ministre)</EditeurSource>
   <Adresse type="géopostale">
      <Ligne>1 rue de Saint-Quentin</Ligne>
      <CodePostal>02100</CodePostal>
      <NomCommune>Fayet</NomCommune>
      <Localisation>
         <Latitude>49.8650016785</Latitude>
         <Longitude>3.25489997864</Longitude>
         <Précision>6</Précision>
      </Localisation>
      <Accessibilité type="NAC"/>
   </Adresse>
   <CoordonnéesNum>
      <Téléphone>+33 3 23 62 57 13</Téléphone>
      <Télécopie>+33 3 23 67 07 33</Télécopie>
      <Email>mairie.fayet@wanadoo.fr</Email>
   </CoordonnéesNum>
   <Ouverture>
      <PlageJ début="lundi" fin="lundi">
         <PlageH début="10:00:00" fin="13:00:00"/>
      </PlageJ>
      <PlageJ début="mardi" fin="mardi">
         <PlageH début="13:30:00" fin="16:30:00"/>
      </PlageJ>
      <PlageJ début="jeudi" fin="jeudi">
         <PlageH début="10:00:00" fin="13:00:00"/>
      </PlageJ>
      <PlageJ début="vendredi" fin="vendredi">
         <PlageH début="13:30:00" fin="16:30:00"/>
      </PlageJ>
      <PlageJ début="samedi" fin="samedi">
         <PlageH début="09:00:00" fin="11:00:00"/>
      </PlageJ>
   </Ouverture>
</Organisme>