<?xml version="1.0" encoding="UTF-8"?>
<Organisme id="mairie-38237-01" codeInsee="38237" dateMiseAJour="2015-07-08"
           pivotLocal="mairie">
   <Nom>Mairie de Mizoën</Nom>
   <EditeurSource>La Direction de l'information légale et administrative (Premier ministre)</EditeurSource>
   <Adresse type="géopostale">
      <Ligne>Le Village</Ligne>
      <CodePostal>38142</CodePostal>
      <NomCommune>Mizoën</NomCommune>
      <Localisation>
         <Latitude>45.0498695374</Latitude>
         <Longitude>6.142786026</Longitude>
         <Précision>4</Précision>
      </Localisation>
      <Accessibilité type="NAC"/>
   </Adresse>
   <CoordonnéesNum>
      <Téléphone>+33 4 76 80 11 39</Téléphone>
      <Télécopie>+33 4 76 80 11 39</Télécopie>
      <Email>mairie.mizoen@wanadoo.fr</Email>
   </CoordonnéesNum>
   <Ouverture>
      <PlageJ début="lundi" fin="lundi">
         <PlageH début="14:00:00" fin="18:00:00"/>
      </PlageJ>
      <PlageJ début="jeudi" fin="jeudi">
         <PlageH début="14:00:00" fin="18:00:00"/>
      </PlageJ>
   </Ouverture>
</Organisme>