<?xml version="1.0" encoding="UTF-8"?>
<Organisme id="afpa-07319-01" codeInsee="07319" dateMiseAJour="2015-09-09"
           pivotLocal="afpa">
   <Nom>Association de formation professionnelle des adultes (Afpa) - Centre du Teil</Nom>
   <EditeurSource>La Direction de l'information légale et administrative (Premier ministre)</EditeurSource>
   <Adresse type="géopostale">
      <Ligne>37 avenue de l'Europe</Ligne>
      <CodePostal>07400</CodePostal>
      <NomCommune>Le Teil</NomCommune>
      <Localisation>
         <Latitude>44.5438977</Latitude>
         <Longitude>4.6876748</Longitude>
         <Précision>8</Précision>
      </Localisation>
   </Adresse>
   <CoordonnéesNum>
      <Téléphone coût="Numéro violet ou majoré. Écoutez le tarif en début d'appel.">3936</Téléphone>
      <Url>http://www.rhone-alpes.afpa.fr</Url>
   </CoordonnéesNum>
</Organisme>