<?xml version="1.0" encoding="UTF-8"?>
<Organisme id="commissariat_police-06083-01" codeInsee="06083" dateMiseAJour="2014-12-30"
           pivotLocal="commissariat_police">
   <Nom>Hôtel de police de Menton</Nom>
   <EditeurSource>Ministère de l'Intérieur</EditeurSource>
   <Adresse type="géopostale">
      <Ligne>8 rue Partouneaux</Ligne>
      <CodePostal>06500</CodePostal>
      <NomCommune>Menton</NomCommune>
      <Localisation>
         <Latitude>43.7748294</Latitude>
         <Longitude>7.4974262</Longitude>
         <Précision>8</Précision>
      </Localisation>
   </Adresse>
   <CoordonnéesNum>
      <Téléphone>+33 4 93 28 66 00</Téléphone>
      <Url>http://www.police-nationale.interieur.gouv.fr</Url>
      <Sve>http://www.interieur.gouv.fr/Contacter-une-brigade-de-gendarmerie-ou-un-commissariat-de-police</Sve>
   </CoordonnéesNum>
</Organisme>