<?xml version="1.0" encoding="UTF-8"?>
<Organisme id="mairie-16153-01" codeInsee="16153" dateMiseAJour="2015-08-12"
           pivotLocal="mairie">
   <Nom>Mairie de Gondeville</Nom>
   <EditeurSource>La Direction de l'information légale et administrative (Premier ministre)</EditeurSource>
   <Adresse type="géopostale">
      <Ligne>1 route Isaac-de-Laisné</Ligne>
      <CodePostal>16200</CodePostal>
      <NomCommune>Gondeville</NomCommune>
      <Localisation>
         <Latitude>45.6707000732</Latitude>
         <Longitude>-0.147310003638</Longitude>
         <Précision>6</Précision>
      </Localisation>
      <Accessibilité type="ACC"/>
   </Adresse>
   <CoordonnéesNum>
      <Téléphone>+33 5 45 81 02 81</Téléphone>
      <Télécopie>+33 5 45 81 79 93</Télécopie>
      <Email>mairiedegondeville@wanadoo.fr</Email>
   </CoordonnéesNum>
   <Ouverture>
      <PlageJ début="lundi" fin="lundi">
         <PlageH début="08:30:00" fin="12:00:00"/>
      </PlageJ>
      <PlageJ début="mercredi" fin="mercredi">
         <PlageH début="09:30:00" fin="12:00:00"/>
         <PlageH début="14:00:00" fin="17:00:00"/>
      </PlageJ>
      <PlageJ début="vendredi" fin="vendredi">
         <PlageH début="08:30:00" fin="12:00:00"/>
      </PlageJ>
   </Ouverture>
</Organisme>