<?xml version="1.0" encoding="UTF-8"?>
<Organisme id="mairie-54110-01" codeInsee="54110" dateMiseAJour="2015-05-12"
           pivotLocal="mairie">
   <Nom>Mairie de Cerville</Nom>
   <EditeurSource>La Direction de l'information légale et administrative (Premier ministre)</EditeurSource>
   <Adresse type="géopostale">
      <Ligne>6 bis rue de l'Église</Ligne>
      <CodePostal>54420</CodePostal>
      <NomCommune>Cerville</NomCommune>
      <Localisation>
         <Latitude>48.6890983582</Latitude>
         <Longitude>6.24827003479</Longitude>
         <Précision>8</Précision>
      </Localisation>
      <Accessibilité type="ACC">plain-pied</Accessibilité>
   </Adresse>
   <CoordonnéesNum>
      <Téléphone>+33 3 83 20 44 04</Téléphone>
      <Télécopie>+33 3 83 20 87 90</Télécopie>
      <Email>mairie.cerville@orange.fr</Email>
   </CoordonnéesNum>
   <Ouverture>
      <PlageJ début="jeudi" fin="jeudi">
         <PlageH début="14:00:00" fin="18:00:00"/>
         <Note>Deuxième permanence.</Note>
      </PlageJ>
      <PlageJ début="lundi" fin="lundi">
         <PlageH début="17:00:00" fin="18:00:00"/>
         <Note>Première permanence.</Note>
      </PlageJ>
      <PlageJ début="vendredi" fin="vendredi">
         <PlageH début="17:00:00" fin="18:30:00"/>
      </PlageJ>
   </Ouverture>
</Organisme>