<?xml version="1.0" encoding="UTF-8"?>
<Organisme id="mairie-59119-01" codeInsee="59119" dateMiseAJour="2015-08-12"
           pivotLocal="mairie">
   <Nom>Mairie de Buysscheure</Nom>
   <EditeurSource>La Direction de l'information légale et administrative (Premier ministre)</EditeurSource>
   <Adresse type="géopostale">
      <Ligne>81 Pauwer-Straete</Ligne>
      <CodePostal>59285</CodePostal>
      <NomCommune>Buysscheure</NomCommune>
      <Localisation>
         <Latitude>50.8022994995</Latitude>
         <Longitude>2.327450037</Longitude>
         <Précision>6</Précision>
      </Localisation>
      <Accessibilité type="ACC"/>
   </Adresse>
   <CoordonnéesNum>
      <Téléphone>+33 3 28 43 01 00</Téléphone>
      <Télécopie>+33 9 72 32 20 38</Télécopie>
      <Email>mairie.buysscheure@wanadoo.fr</Email>
      <Url>http://www.buysscheure.fr</Url>
   </CoordonnéesNum>
   <Ouverture>
      <PlageJ début="lundi" fin="lundi">
         <PlageH début="09:00:00" fin="11:30:00"/>
      </PlageJ>
      <PlageJ début="jeudi" fin="jeudi">
         <PlageH début="16:00:00" fin="18:30:00"/>
      </PlageJ>
      <PlageJ début="samedi" fin="samedi">
         <PlageH début="09:00:00" fin="11:00:00"/>
      </PlageJ>
   </Ouverture>
</Organisme>