<?xml version="1.0" encoding="UTF-8"?>
<Organisme id="mairie-65071-01" codeInsee="65071" dateMiseAJour="2013-05-15"
           pivotLocal="mairie">
   <Nom>Mairie de Batsère</Nom>
   <EditeurSource>La Direction de l'information légale et administrative (Premier ministre)</EditeurSource>
   <Adresse type="géopostale">
      <Ligne>Place Jean-Laforgue</Ligne>
      <CodePostal>65130</CodePostal>
      <NomCommune>Batsère</NomCommune>
      <Localisation>
         <Latitude>43.0612183</Latitude>
         <Longitude>0.2887647</Longitude>
         <Précision>4</Précision>
      </Localisation>
      <Accessibilité type="ACC"/>
   </Adresse>
   <CoordonnéesNum>
      <Téléphone coût="tarification selon l’opérateur">+33 6 75 05 15 66</Téléphone>
   </CoordonnéesNum>
   <Ouverture>
      <PlageJ début="mardi" fin="mardi">
         <PlageH début="09:00:00" fin="12:00:00"/>
      </PlageJ>
   </Ouverture>
</Organisme>