<?xml version="1.0" encoding="UTF-8"?>
<Organisme id="mairie-78291-01" codeInsee="78291" dateMiseAJour="2015-05-12"
           pivotLocal="mairie">
   <Nom>Mairie de Guerville</Nom>
   <EditeurSource>La Direction de l'information légale et administrative (Premier ministre)</EditeurSource>
   <Adresse type="géopostale">
      <Ligne>4 place de la Mairie</Ligne>
      <CodePostal>78930</CodePostal>
      <NomCommune>Guerville</NomCommune>
      <Localisation>
         <Latitude>48.9447959</Latitude>
         <Longitude>1.734788</Longitude>
         <Précision>6</Précision>
      </Localisation>
      <Accessibilité type="ACC"/>
   </Adresse>
   <CoordonnéesNum>
      <Téléphone>+33 1 30 42 63 22</Téléphone>
      <Télécopie>+33 1 30 42 33 11</Télécopie>
      <Email>mairie.guerville@guerville.org</Email>
      <Url>http://www.guerville.fr</Url>
   </CoordonnéesNum>
   <Ouverture>
      <PlageJ début="jeudi" fin="vendredi">
         <PlageH début="08:30:00" fin="12:00:00"/>
         <PlageH début="13:30:00" fin="18:00:00"/>
      </PlageJ>
      <PlageJ début="lundi" fin="lundi">
         <PlageH début="08:30:00" fin="12:00:00"/>
         <PlageH début="13:30:00" fin="18:00:00"/>
      </PlageJ>
      <PlageJ début="mercredi" fin="mercredi">
         <PlageH début="13:30:00" fin="18:00:00"/>
      </PlageJ>
      <PlageJ début="samedi" fin="samedi">
         <PlageH début="09:00:00" fin="12:00:00"/>
      </PlageJ>
   </Ouverture>
</Organisme>