<?xml version="1.0" encoding="UTF-8"?>
<Organisme id="commissariat_police-31555-08" codeInsee="31555" dateMiseAJour="2014-12-30"
           pivotLocal="commissariat_police">
   <Nom>Commissariat subdivisionnaire de police de Toulouse</Nom>
   <EditeurSource>Ministère de l'Intérieur</EditeurSource>
   <Adresse type="géopostale">
      <Ligne>3 rue Raymond-Corraze</Ligne>
      <Ligne>Quartier Ormeau</Ligne>
      <CodePostal>31000</CodePostal>
      <NomCommune>Toulouse</NomCommune>
      <Localisation>
         <Latitude>43.5795495</Latitude>
         <Longitude>1.4841685</Longitude>
         <Précision>8</Précision>
      </Localisation>
   </Adresse>
   <CoordonnéesNum>
      <Téléphone>+33 5 61 80 45 41</Téléphone>
      <Url>http://www.police-nationale.interieur.gouv.fr</Url>
      <Sve>http://www.interieur.gouv.fr/Contacter-une-brigade-de-gendarmerie-ou-un-commissariat-de-police</Sve>
   </CoordonnéesNum>
</Organisme>