<?xml version="1.0" encoding="UTF-8"?>
<Organisme codeInsee="31555" dateMiseAJour="2015-11-03" id="permanence_juridique-31555-12" idPresta="4cd18fb42935940531010a96" pivotLocal="permanence_juridique">
    <Nom>Point d&#39;accès au droit</Nom>
    <EditeurSource>Ministère de la justice</EditeurSource>
    <EditeurEMail>support-donnees@comarquage.fr</EditeurEMail>
    <Adresse type="géopostale">
        <Ligne>Mairie annexe Saint-Simon</Ligne>
        <Ligne>1 place de l&#39;Eglise</Ligne>
        <CodePostal>31000</CodePostal>
        <NomCommune>TOULOUSE</NomCommune>
        <Localisation>
            <Latitude>43.557424</Latitude>
            <Longitude>1.380798</Longitude>
            <Précision>6</Précision>
        </Localisation>
    </Adresse>
    <CoordonnéesNum>
        <Téléphone>+33 5 61 06 40 10</Téléphone>
        <Sve>http://www.justice.gouv.fr/sve</Sve>
    </CoordonnéesNum>
</Organisme>