<?xml version="1.0" encoding="UTF-8"?>
<Organisme id="gendarmerie-24448-01" codeInsee="24448" dateMiseAJour="2015-03-23"
           pivotLocal="gendarmerie">
   <Nom>Brigade de proximité de gendarmerie de Saint-Martial-d'Albarède</Nom>
   <EditeurSource>Ministère de l'Intérieur</EditeurSource>
   <Adresse type="géopostale">
      <Ligne>36 avenue de la Résistance</Ligne>
      <CodePostal>24160</CodePostal>
      <NomCommune>Saint-Martial-d'Albarède</NomCommune>
      <Localisation>
         <Latitude>45.326377</Latitude>
         <Longitude>1.031781</Longitude>
         <Précision>8</Précision>
      </Localisation>
   </Adresse>
   <CoordonnéesNum>
      <Téléphone>+33 5 53 55 38 90</Téléphone>
      <Télécopie>+33 5 53 55 38 93</Télécopie>
      <Url>http://www.gendarmerie.interieur.gouv.fr</Url>
      <Sve>http://www.interieur.gouv.fr/Contacter-une-brigade-de-gendarmerie-ou-un-commissariat-de-police</Sve>
   </CoordonnéesNum>
</Organisme>