<?xml version="1.0" encoding="UTF-8"?>
<Organisme id="gendarmerie-24571-01" codeInsee="24571" dateMiseAJour="2015-03-23"
           pivotLocal="gendarmerie">
   <Nom>Brigade de proximité de gendarmerie de Vergt</Nom>
   <EditeurSource>Ministère de l'Intérieur</EditeurSource>
   <Adresse type="géopostale">
      <Ligne>21 rue du Château-Vieux</Ligne>
      <CodePostal>24380</CodePostal>
      <NomCommune>Vergt</NomCommune>
      <Localisation>
         <Latitude>45.024192</Latitude>
         <Longitude>0.717979</Longitude>
         <Précision>8</Précision>
      </Localisation>
   </Adresse>
   <CoordonnéesNum>
      <Téléphone>+33 5 53 07 89 75</Téléphone>
      <Télécopie>+33 5 53 07 89 78</Télécopie>
      <Url>http://www.gendarmerie.interieur.gouv.fr</Url>
      <Sve>http://www.interieur.gouv.fr/Contacter-une-brigade-de-gendarmerie-ou-un-commissariat-de-police</Sve>
   </CoordonnéesNum>
</Organisme>