<?xml version="1.0" encoding="UTF-8"?>
<Organisme id="epci-63261-01" codeInsee="63261" dateMiseAJour="2015-05-12"
           pivotLocal="epci">
   <Nom>Communauté de communes des Côteaux de l'Allier</Nom>
   <EditeurSource>La Direction de l'information légale et administrative (Premier ministre)</EditeurSource>
   <Adresse type="géopostale">
      <Ligne>Lieu-dit Le Chauffour</Ligne>
      <Ligne>3 rue de Brenat</Ligne>
      <CodePostal>63500</CodePostal>
      <NomCommune>Orbeil</NomCommune>
      <Localisation>
         <Latitude>45.5599927</Latitude>
         <Longitude>3.2882379</Longitude>
         <Précision>6</Précision>
      </Localisation>
      <Accessibilité type="NAC"/>
   </Adresse>
   <CoordonnéesNum>
      <Téléphone>+33 4 73 55 01 17</Téléphone>
      <Télécopie>+33 4 73 55 96 02</Télécopie>
      <Email>descoteaux.allier@wanadoo.fr</Email>
      <Url>http://www.coteaux-allier.fr</Url>
   </CoordonnéesNum>
   <Ouverture>
      <PlageJ début="lundi" fin="vendredi">
         <PlageH début="08:30:00" fin="12:00:00"/>
         <PlageH début="13:30:00" fin="17:00:00"/>
      </PlageJ>
   </Ouverture>
</Organisme>