<?xml version="1.0" encoding="UTF-8"?>
<Organisme codeInsee="54395" dateMiseAJour="2016-02-12" id="mjd-54395-01" idPresta="51b08cbfb473e41478000ced" pivotLocal="mjd">
    <Nom>Maison de justice et du droit  de Nancy</Nom>
    <EditeurSource>Ministère de la justice</EditeurSource>
    <EditeurEMail>support-donnees@comarquage.fr</EditeurEMail>
    <Adresse type="géopostale">
        <Ligne>17 bis rue Laurent Bonnevay</Ligne>
        <Ligne>Bâtiment Tilleul Argenté</Ligne>
        <CodePostal>54100</CodePostal>
        <NomCommune>NANCY</NomCommune>
        <Localisation>
            <Latitude>48.70257</Latitude>
            <Longitude>6.156337</Longitude>
            <Précision>8</Précision>
        </Localisation>
    </Adresse>
    <CoordonnéesNum>
        <Téléphone>+33 3 83 97 03 11</Téléphone>
        <Télécopie>+33 3 83 97 08 76</Télécopie>
        <Email>mailto:mjd-nancy@justice.fr</Email>
        <Url>http://www.justice.gouv.fr/</Url>
        <Sve>http://www.justice.gouv.fr/sve</Sve>
    </CoordonnéesNum>
    <Ouverture>
        <PlageJ début="lundi" fin="vendredi">
            <PlageH début="09:00:00" fin="12:00:00"/>
            <PlageH début="13:45:00" fin="17:15:00"/>
        </PlageJ>
    </Ouverture>
</Organisme>