<?xml version="1.0" encoding="UTF-8"?>
<Organisme id="afpa-14341-01" codeInsee="14341" dateMiseAJour="2015-09-09"
           pivotLocal="afpa">
   <Nom>Association de formation professionnelle des adultes (Afpa) - Centre d'Ifs</Nom>
   <EditeurSource>La Direction de l'information légale et administrative (Premier ministre)</EditeurSource>
   <Adresse type="géopostale">
      <Ligne>Rue Anton-Tchekhov</Ligne>
      <CodePostal>14123</CodePostal>
      <NomCommune>Ifs</NomCommune>
      <Localisation>
         <Latitude>49.14851</Latitude>
         <Longitude>-0.352456</Longitude>
         <Précision>8</Précision>
      </Localisation>
   </Adresse>
   <CoordonnéesNum>
      <Téléphone coût="Numéro violet ou majoré. Écoutez le tarif en début d'appel.">3936</Téléphone>
      <Télécopie>+33 2 31 35 65 12</Télécopie>
      <Url>http://www.basse-normandie.afpa.fr</Url>
   </CoordonnéesNum>
</Organisme>