<?xml version="1.0" encoding="UTF-8"?>
<Organisme id="pole_emploi-75108-01" codeInsee="75108" dateMiseAJour="2015-09-09"
           pivotLocal="pole_emploi">
   <Nom>Pôle emploi de Paris 7e, 8e et 9e arrondissements - Saint-Pétersbourg</Nom>
   <EditeurSource>La Direction de l'information légale et administrative (Premier ministre)</EditeurSource>
   <Adresse type="géopostale">
      <Ligne>34 rue Saint-Pétersbourg</Ligne>
      <CodePostal>75008</CodePostal>
      <NomCommune>Paris</NomCommune>
      <Localisation>
         <Latitude>48.8824739</Latitude>
         <Longitude>2.3263512</Longitude>
         <Précision>8</Précision>
      </Localisation>
   </Adresse>
   <CoordonnéesNum>
      <Téléphone coût="Numéro violet ou majoré : prix d'un appel + service gratuit. Depuis l’étranger, vous pouvez composer le +33 1 77 86 39 49. Employeur : 3995. Depuis l'étranger, composez le +33 1 77 86 39 95.">3949</Téléphone>
      <Url>http://www.pole-emploi.fr</Url>
   </CoordonnéesNum>
   <Ouverture>
      <PlageJ début="vendredi" fin="vendredi">
         <PlageH début="09:00:00" fin="12:00:00"/>
      </PlageJ>
      <PlageJ début="lundi" fin="jeudi">
         <PlageH début="09:00:00" fin="17:00:00"/>
      </PlageJ>
   </Ouverture>
</Organisme>