<?xml version="1.0" encoding="UTF-8"?>
<Organisme id="tresorerie-46185-01" codeInsee="46185" dateMiseAJour="2015-12-11"
           pivotLocal="tresorerie">
   <Nom>Trésorerie de Martel</Nom>
   <EditeurSource>La Direction de l'information légale et administrative (Premier ministre)</EditeurSource>
   <Adresse type="géopostale">
      <Ligne>Avenue de Nassogne</Ligne>
      <CodePostal>46600</CodePostal>
      <NomCommune>Martel</NomCommune>
      <Localisation>
         <Latitude>44.934533</Latitude>
         <Longitude>1.60749</Longitude>
         <Précision>8</Précision>
      </Localisation>
      <Accessibilité type="NAC"/>
   </Adresse>
   <CoordonnéesNum>
      <Téléphone>+33 5 65 37 30 31</Téléphone>
      <Télécopie>+33 5 65 37 44 20</Télécopie>
      <Email>t046020@dgfip.finances.gouv.fr</Email>
      <Url>http://www.impots.gouv.fr</Url>
   </CoordonnéesNum>
   <Ouverture>
      <PlageJ début="mardi" fin="jeudi">
         <PlageH début="09:00:00" fin="12:30:00"/>
         <PlageH début="14:00:00" fin="16:00:00"/>
      </PlageJ>
   </Ouverture>
</Organisme>