<?xml version="1.0" encoding="UTF-8"?>
<Organisme id="clic-2B134-01" codeInsee="2B134" dateMiseAJour="2015-04-29"
           pivotLocal="clic"
           idPresta="clic-165">
   <Nom>Point d'information local dédié aux personnes âgées - L'Ile-Rousse</Nom>
   <EditeurSource>Caisse nationale de solidarité pour l'autonomie</EditeurSource>
   <Adresse type="géopostale">
      <Ligne>Centre local d'information et de coordination de Balagne</Ligne>
      <Ligne>Place Delaunay</Ligne>
      <CodePostal>20220</CodePostal>
      <NomCommune>L'Ile-Rousse</NomCommune>
      <Localisation>
         <Latitude>42.632898</Latitude>
         <Longitude>8.937697</Longitude>
         <Précision>8</Précision>
      </Localisation>
   </Adresse>
   <CoordonnéesNum>
      <Téléphone>+33 4 95 60 81 81</Téléphone>
      <Email>amlucciani@cg2b.fr</Email>
   </CoordonnéesNum>
   <Ouverture>
      <PlageJ début="lundi" fin="jeudi">
         <PlageH début="08:00:00" fin="12:00:00"/>
         <PlageH début="13:00:00" fin="17:00:00"/>
      </PlageJ>
      <PlageJ début="vendredi" fin="vendredi">
         <PlageH début="08:00:00" fin="12:00:00"/>
         <PlageH début="13:00:00" fin="16:00:00"/>
      </PlageJ>
   </Ouverture>
   <Commentaire>Téléphoner pour convenir d'un rendez-vous avant de se rendre sur place.</Commentaire>
</Organisme>